deepsea_ai/__init__.py
deepsea_ai/__main__.py
deepsea_ai/cdk/DEV.md
deepsea_ai/cdk/app/.gitignore
deepsea_ai/cdk/app/.npmignore
deepsea_ai/cdk/app/bin/deploy_stack.ts
deepsea_ai/cdk/app/cdk.json
deepsea_ai/cdk/app/config1280.yml
deepsea_ai/cdk/app/config640.yml
deepsea_ai/cdk/app/lib/config.ts
deepsea_ai/cdk/app/lib/ecs_task_autoscaling.ts
deepsea_ai/cdk/app/package-lock.json
deepsea_ai/cdk/app/package.json
deepsea_ai/cdk/app/tsconfig.json
deepsea_ai/cdk/deploy.sh
deepsea_ai/cdk/destroy.sh
deepsea_ai/commands/__init__.py
deepsea_ai/commands/bucket.py
deepsea_ai/commands/monitor.py
deepsea_ai/commands/monitor_utils.py
deepsea_ai/commands/process.py
deepsea_ai/commands/train.py
deepsea_ai/commands/upload_tag.py
deepsea_ai/common_args.py
deepsea_ai/config/__init__.py
deepsea_ai/config/config.ini
deepsea_ai/config/config.py
deepsea_ai/config/setup.py
deepsea_ai/database/job/__init__.py
deepsea_ai/database/job/database.py
deepsea_ai/database/job/database_helper.py
deepsea_ai/database/job/misc.py
deepsea_ai/database/report_generator.py
deepsea_ai/database/tracks/__init__.py
deepsea_ai/database/tracks/api.py
deepsea_ai/database/tracks/queries.py
deepsea_ai/logger/__init__.py
deepsea_ai/pipeline/__init__.py
deepsea_ai/pipeline/run_strongsort.py
deepsea_ai-1.25.0.dist-info/LICENSE
deepsea_ai-1.25.0.dist-info/METADATA
deepsea_ai-1.25.0.dist-info/WHEEL
deepsea_ai-1.25.0.dist-info/entry_points.txt
deepsea_ai-1.25.0.dist-info/RECORD
