Metadata-Version: 2.1
Name: deepsea-ai
Version: 1.25.0
Summary: DeepSeaAI is a Python package to simplify processing deep sea video in AWS from a command line.
Home-page: https://github.com/mbari-org/deepsea-ai
License: Apache License 2.0 
Author: Danelle Cline
Author-email: dcline@mbari.org
Requires-Python: >=3.10,<3.12
Classifier: Development Status :: 1 - Planning
Classifier: Environment :: Console
Classifier: Environment :: Web Environment
Classifier: Intended Audience :: Developers
Classifier: Intended Audience :: Science/Research
Classifier: License :: OSI Approved :: Apache Software License
Classifier: License :: Other/Proprietary License
Classifier: Operating System :: OS Independent
Classifier: Programming Language :: Python :: 3
Classifier: Programming Language :: Python :: 3.10
Classifier: Programming Language :: Python :: 3.11
Classifier: Topic :: Multimedia :: Video
Classifier: Topic :: Scientific/Engineering :: Artificial Intelligence
Classifier: Topic :: Scientific/Engineering :: Image Recognition
Requires-Dist: awscli (>=1.25.71,<2.0.0)
Requires-Dist: boto3 (>=1.24.70,<2.0.0)
Requires-Dist: click (>=8.0.0,<9.0.0)
Requires-Dist: numpy (>=1.23.3,<2.0.0)
Requires-Dist: pydantic-sqlalchemy (>=0.0.9,<0.0.10)
Requires-Dist: requests (>=2.26.0,<3.0.0)
Requires-Dist: sagemaker (>=2.102.0,<3.0.0)
Requires-Dist: sqlalchemy (>=1.4.26,<2.0.0)
Requires-Dist: tqdm (>=4.41.0,<5.0.0)
Project-URL: Repository, https://github.com/mbari-org/deepsea-ai
